tutorial/q2/counter.sv
module counter #(
    parameter WIDTH=8  // number of bits
)(
    input logic clk, 
    input logic rst_n, // async active low reset
    input logic en,
    input logic up, // 1: count up, 0: count down
    output logic [WIDTH-1:0] q
);

    always_ff @(posedge clk or posedge rst_n) begin // sequential logic with unblocking assignment
        if (rst_n)
            q <= '0;   // reset to 0
        else if (en)
            q <= up ? (q+1'b1) : (q-1'b1);  //combinational logic
    end
endmodule

tutorial/q2/tb_counter.sv
`timescale 1ns/1ps
`default_nettype none

module tb_counter;
    parameter WIDTH=4; // number of bits

    logic clk=0, rst_n=0, en=0, up=1;
    logic [WIDTH-1:0] q;

    counter #( .WIDTH(WIDTH) ) dut (
        .clk(clk),
        .rst_n(rst_n),
        .en(en),
        .up(up),
        .q(q)
    );

    //100MHz-ish clock
    always #5 clk = ~clk; // 10 time units clock period

    task step(input int n=1);
        repeat (n) @(posedge clk);
    endtask

    initial begin
        $dumpfile("tb_counter.vcd");
        $dumpvars(0, tb_counter);

        //release reset
        step(1);
        rst_n = 1; // release reset
        step(1);
        rst_n = 0; // assert reset
        // step(1);

        //count up 3 stages
        en=1; up=1; step(3);
        assert(q == 3) else $fatal(1, "Up count failed q=%0d", q);

        //count down 2 stages 
        up=0; step(2);
        assert(q == 1) else $fatal(1, "Down Count failed q=%0d", q);

        //hold
        en=0; step(3); #1
        assert(q == 1) else $fatal(1, "Hold failed");

        $display("[COUNTER] All tests completed");
        $finish;
    end
endmodule

`default_nettype wire

tutorial/q2/tb_counter.vcd
$date
	Fri Sep 26 11:42:40 2025
$end
$version
	Icarus Verilog
$end
$timescale
	1ps
$end
$scope module tb_counter $end
$var wire 4 ! q [3:0] $end
$var reg 1 " clk $end
$var reg 1 # en $end
$var reg 1 $ rst_n $end
$var reg 1 % up $end
$scope module dut $end
$var wire 1 " clk $end
$var wire 1 # en $end
$var wire 1 $ rst_n $end
$var wire 1 % up $end
$var reg 4 & q [3:0] $end
$upscope $end
$scope task step $end
$var integer 32 ' n [31:0] $end
$upscope $end
$upscope $end
$enddefinitions $end
#0
$dumpvars
b1 '
bx &
1%
0$
0#
0"
bx !
$end
#5000
b0 !
b0 &
1$
1"
#10000
0"
#15000
b1 !
b1 &
b11 '
1#
0$
1"
#20000
0"
#25000
b10 !
b10 &
1"
#30000
0"
#35000
b11 !
b11 &
1"
#40000
0"
#45000
b10 !
b10 &
b10 '
0%
1"
#50000
0"
#55000
b1 !
b1 &
1"
#60000
0"
#65000
b11 '
0#
1"
