fsm-assignments/problem2_traffic/traffic_light.v
module traffic_light(
    input  wire clk,
    input  wire rst,         // sync active-high
    input  wire tick,        // 1-cycle per-second pulse
    output wire ns_g, ns_y, ns_r,
    output wire ew_g, ew_y, ew_r
);

    // 1. Define States using parameters for readability
    parameter NS_GREEN  = 2'b00;
    parameter NS_YELLOW = 2'b01;
    parameter EW_GREEN  = 2'b10;
    parameter EW_YELLOW = 2'b11;

    // Define timing constants
    parameter GREEN_TICKS = 5;
    parameter YELLOW_TICKS = 2;

    // 2. Internal Registers
    reg [1:0] current_state, next_state;
    reg [2:0] tick_counter; // Counter needs to hold up to 5, so 3 bits is enough

    // 3. Sequential Logic: State Register and Per-Phase Counter
    always @(posedge clk) begin
        if (rst) begin
            current_state <= NS_GREEN;
            tick_counter  <= 0;
        end else begin
            // On a state change, reset the counter. Otherwise, update the state.
            if (current_state != next_state) begin
                tick_counter <= 0;
            end else if (tick) begin // Increment counter only on a tick
                tick_counter <= tick_counter + 1;
            end
            current_state <= next_state;
        end
    end

    // 4. Combinational Logic: Next State Determination
    always @(*) begin
        next_state = current_state; // Default: stay in the same state
        case (current_state)
            NS_GREEN: begin
                if (tick && (tick_counter == GREEN_TICKS - 1)) begin
                    next_state = NS_YELLOW;
                end
            end
            NS_YELLOW: begin
                if (tick && (tick_counter == YELLOW_TICKS - 1)) begin
                    next_state = EW_GREEN;
                end
            end
            EW_GREEN: begin
                if (tick && (tick_counter == GREEN_TICKS - 1)) begin
                    next_state = EW_YELLOW;
                end
            end
            EW_YELLOW: begin
                if (tick && (tick_counter == YELLOW_TICKS - 1)) begin
                    next_state = NS_GREEN;
                end
            end
            default: next_state = NS_GREEN;
        endcase
    end

    // 5. Combinational Logic: Output Determination (Moore FSM)
    // Outputs are assigned using intermediate registers to be set by the case statement.
    reg ns_g_reg, ns_y_reg, ns_r_reg;
    reg ew_g_reg, ew_y_reg, ew_r_reg;

    assign ns_g = ns_g_reg;
    assign ns_y = ns_y_reg;
    assign ns_r = ns_r_reg;
    assign ew_g = ew_g_reg;
    assign ew_y = ew_y_reg;
    assign ew_r = ew_r_reg;

    always @(*) begin
        // Default all lights to off to avoid latches
        {ns_g_reg, ns_y_reg, ns_r_reg} = 3'b000;
        {ew_g_reg, ew_y_reg, ew_r_reg} = 3'b000;

        case (current_state)
            NS_GREEN: begin
                ns_g_reg = 1'b1; // NS is Green
                ew_r_reg = 1'b1; // EW is Red
            end
            NS_YELLOW: begin
                ns_y_reg = 1'b1; // NS is Yellow
                ew_r_reg = 1'b1; // EW is Red
            end
            EW_GREEN: begin
                ew_g_reg = 1'b1; // EW is Green
                ns_r_reg = 1'b1; // NS is Red
            end
            EW_YELLOW: begin
                ew_y_reg = 1'b1; // EW is Yellow
                ns_r_reg = 1'b1; // NS is Red
            end
            default: begin // Default to a safe state (all red)
                ns_r_reg = 1'b1;
                ew_r_reg = 1'b1;
            end
        endcase
    end

endmodule

fsm-assignments/problem2_traffic/tb_traffic_light.v
`timescale 1ns/1ps
`include "traffic_light.v"

// Testbench for traffic_light module
module tb_traffic_light;

    // 1. Testbench Signals
    reg clk;
    reg rst;
    reg tick;

    wire ns_g, ns_y, ns_r;
    wire ew_g, ew_y, ew_r;

    // 2. Instantiate the Device Under Test (DUT)
    traffic_light dut (
        .clk(clk),
        .rst(rst),
        .tick(tick),
        .ns_g(ns_g), .ns_y(ns_y), .ns_r(ns_r),
        .ew_g(ew_g), .ew_y(ew_y), .ew_r(ew_r)
    );

    // 3. Clock Generator (e.g., 100MHz clock -> 10ns period)
    parameter CLK_PERIOD = 10;
    initial begin
        clk = 0;
        forever #(CLK_PERIOD/2) clk = ~clk;
    end

    // 4. Tick Generator (produces a 1-cycle pulse every 10 clock cycles)
    // This simulates the 1Hz tick in an efficient way.
    integer tick_gen_counter = 0;
    always @(posedge clk) begin
        if (rst) begin
            tick <= 0;
            tick_gen_counter <= 0;
        end else begin
            if (tick_gen_counter == 9) begin
                tick <= 1;
                tick_gen_counter <= 0;
            end else begin
                tick <= 0;
                tick_gen_counter <= tick_gen_counter + 1;
            end
        end
    end

    // 5. Simulation Control and Stimulus
    initial begin
        // For waveform viewing
        $dumpfile("dump.vcd");
        $dumpvars(0, tb_traffic_light);

        // Apply reset
        rst = 1;
        tick = 0;
        @(posedge clk);
        @(posedge clk);
        rst = 0;

        // Run simulation for a few full cycles and then stop
        #2000; // Run for 2000 time units
        $finish;
    end

endmodule

fsm-assignments/problem2_traffic/waves/dump.vcd
$date
	Tue Aug 19 20:24:33 2025
$end
$version
	Icarus Verilog
$end
$timescale
	1ps
$end
$scope module tb_traffic_light $end
$var wire 1 ! ns_y $end
$var wire 1 " ns_r $end
$var wire 1 # ns_g $end
$var wire 1 $ ew_y $end
$var wire 1 % ew_r $end
$var wire 1 & ew_g $end
$var reg 1 ' clk $end
$var reg 1 ( rst $end
$var reg 1 ) tick $end
$var integer 32 * tick_gen_counter [31:0] $end
$scope module dut $end
$var wire 1 ' clk $end
$var wire 1 & ew_g $end
$var wire 1 % ew_r $end
$var wire 1 $ ew_y $end
$var wire 1 # ns_g $end
$var wire 1 " ns_r $end
$var wire 1 ! ns_y $end
$var wire 1 ( rst $end
$var wire 1 ) tick $end
$var reg 2 + current_state [1:0] $end
$var reg 1 , ew_g_reg $end
$var reg 1 - ew_r_reg $end
$var reg 1 . ew_y_reg $end
$var reg 2 / next_state [1:0] $end
$var reg 1 0 ns_g_reg $end
$var reg 1 1 ns_r_reg $end
$var reg 1 2 ns_y_reg $end
$var reg 3 3 tick_counter [2:0] $end
$upscope $end
$upscope $end
$enddefinitions $end
#0
$dumpvars
bx 3
x2
x1
x0
b0 /
x.
x-
x,
bx +
b0 *
0)
1(
0'
x&
x%
x$
x#
x"
x!
$end
#5000
0&
0,
0$
0.
1%
1-
1#
10
0!
02
0"
01
b0 3
b0 +
1'
#10000
0'
#15000
0(
1'
#20000
0'
#25000
b1 *
1'
#30000
0'
#35000
b10 *
1'
#40000
0'
#45000
b11 *
1'
#50000
0'
#55000
b100 *
1'
#60000
0'
#65000
b101 *
1'
#70000
0'
#75000
b110 *
1'
#80000
0'
#85000
b111 *
1'
#90000
0'
#95000
b1000 *
1'
#100000
0'
#105000
b1001 *
1'
#110000
0'
#115000
b0 *
1)
1'
#120000
0'
#125000
b1 3
b1 *
0)
1'
#130000
0'
#135000
b10 *
1'
#140000
0'
#145000
b11 *
1'
#150000
0'
#155000
b100 *
1'
#160000
0'
#165000
b101 *
1'
#170000
0'
#175000
b110 *
1'
#180000
0'
#185000
b111 *
1'
#190000
0'
#195000
b1000 *
1'
#200000
0'
#205000
b1001 *
1'
#210000
0'
#215000
b0 *
1)
1'
#220000
0'
#225000
b10 3
b1 *
0)
1'
#230000
0'
#235000
b10 *
1'
#240000
0'
#245000
b11 *
1'
#250000
0'
#255000
b100 *
1'
#260000
0'
#265000
b101 *
1'
#270000
0'
#275000
b110 *
1'
#280000
0'
#285000
b111 *
1'
#290000
0'
#295000
b1000 *
1'
#300000
0'
#305000
b1001 *
1'
#310000
0'
#315000
b0 *
1)
1'
#320000
0'
#325000
b11 3
b1 *
0)
1'
#330000
0'
#335000
b10 *
1'
#340000
0'
#345000
b11 *
1'
#350000
0'
#355000
b100 *
1'
#360000
0'
#365000
b101 *
1'
#370000
0'
#375000
b110 *
1'
#380000
0'
#385000
b111 *
1'
#390000
0'
#395000
b1000 *
1'
#400000
0'
#405000
b1001 *
1'
#410000
0'
#415000
b0 *
1)
1'
#420000
0'
#425000
b100 3
b1 *
0)
1'
#430000
0'
#435000
b10 *
1'
#440000
0'
#445000
b11 *
1'
#450000
0'
#455000
b100 *
1'
#460000
0'
#465000
b101 *
1'
#470000
0'
#475000
b110 *
1'
#480000
0'
#485000
b111 *
1'
#490000
0'
#495000
b1000 *
1'
#500000
0'
#505000
b1001 *
1'
#510000
0'
#515000
b1 /
b0 *
1)
1'
#520000
0'
#525000
1!
12
1%
1-
0#
00
b1 +
b0 3
b1 *
0)
1'
#530000
0'
#535000
b10 *
1'
#540000
0'
#545000
b11 *
1'
#550000
0'
#555000
b100 *
1'
#560000
0'
#565000
b101 *
1'
#570000
0'
#575000
b110 *
1'
#580000
0'
#585000
b111 *
1'
#590000
0'
#595000
b1000 *
1'
#600000
0'
#605000
b1001 *
1'
#610000
0'
#615000
b0 *
1)
1'
#620000
0'
#625000
b1 3
b1 *
0)
1'
#630000
0'
#635000
b10 *
1'
#640000
0'
#645000
b11 *
1'
#650000
0'
#655000
b100 *
1'
#660000
0'
#665000
b101 *
1'
#670000
0'
#675000
b110 *
1'
#680000
0'
#685000
b111 *
1'
#690000
0'
#695000
b1000 *
1'
#700000
0'
#705000
b1001 *
1'
#710000
0'
#715000
b10 /
b0 *
1)
1'
#720000
0'
#725000
1"
11
1&
1,
0%
0-
0!
02
b10 +
b0 3
b1 *
0)
1'
#730000
0'
#735000
b10 *
1'
#740000
0'
#745000
b11 *
1'
#750000
0'
#755000
b100 *
1'
#760000
0'
#765000
b101 *
1'
#770000
0'
#775000
b110 *
1'
#780000
0'
#785000
b111 *
1'
#790000
0'
#795000
b1000 *
1'
#800000
0'
#805000
b1001 *
1'
#810000
0'
#815000
b0 *
1)
1'
#820000
0'
#825000
b1 3
b1 *
0)
1'
#830000
0'
#835000
b10 *
1'
#840000
0'
#845000
b11 *
1'
#850000
0'
#855000
b100 *
1'
#860000
0'
#865000
b101 *
1'
#870000
0'
#875000
b110 *
1'
#880000
0'
#885000
b111 *
1'
#890000
0'
#895000
b1000 *
1'
#900000
0'
#905000
b1001 *
1'
#910000
0'
#915000
b0 *
1)
1'
#920000
0'
#925000
b10 3
b1 *
0)
1'
#930000
0'
#935000
b10 *
1'
#940000
0'
#945000
b11 *
1'
#950000
0'
#955000
b100 *
1'
#960000
0'
#965000
b101 *
1'
#970000
0'
#975000
b110 *
1'
#980000
0'
#985000
b111 *
1'
#990000
0'
#995000
b1000 *
1'
#1000000
0'
#1005000
b1001 *
1'
#1010000
0'
#1015000
b0 *
1)
1'
#1020000
0'
#1025000
b11 3
b1 *
0)
1'
#1030000
0'
#1035000
b10 *
1'
#1040000
0'
#1045000
b11 *
1'
#1050000
0'
#1055000
b100 *
1'
#1060000
0'
#1065000
b101 *
1'
#1070000
0'
#1075000
b110 *
1'
#1080000
0'
#1085000
b111 *
1'
#1090000
0'
#1095000
b1000 *
1'
#1100000
0'
#1105000
b1001 *
1'
#1110000
0'
#1115000
b0 *
1)
1'
#1120000
0'
#1125000
b100 3
b1 *
0)
1'
#1130000
0'
#1135000
b10 *
1'
#1140000
0'
#1145000
b11 *
1'
#1150000
0'
#1155000
b100 *
1'
#1160000
0'
#1165000
b101 *
1'
#1170000
0'
#1175000
b110 *
1'
#1180000
0'
#1185000
b111 *
1'
#1190000
0'
#1195000
b1000 *
1'
#1200000
0'
#1205000
b1001 *
1'
#1210000
0'
#1215000
b11 /
b0 *
1)
1'
#1220000
0'
#1225000
1$
1.
0&
0,
1"
11
b11 +
b0 3
b1 *
0)
1'
#1230000
0'
#1235000
b10 *
1'
#1240000
0'
#1245000
b11 *
1'
#1250000
0'
#1255000
b100 *
1'
#1260000
0'
#1265000
b101 *
1'
#1270000
0'
#1275000
b110 *
1'
#1280000
0'
#1285000
b111 *
1'
#1290000
0'
#1295000
b1000 *
1'
#1300000
0'
#1305000
b1001 *
1'
#1310000
0'
#1315000
b0 *
1)
1'
#1320000
0'
#1325000
b1 3
b1 *
0)
1'
#1330000
0'
#1335000
b10 *
1'
#1340000
0'
#1345000
b11 *
1'
#1350000
0'
#1355000
b100 *
1'
#1360000
0'
#1365000
b101 *
1'
#1370000
0'
#1375000
b110 *
1'
#1380000
0'
#1385000
b111 *
1'
#1390000
0'
#1395000
b1000 *
1'
#1400000
0'
#1405000
b1001 *
1'
#1410000
0'
#1415000
b0 /
b0 *
1)
1'
#1420000
0'
#1425000
1%
1-
1#
10
0$
0.
0"
01
b0 +
b0 3
b1 *
0)
1'
#1430000
0'
#1435000
b10 *
1'
#1440000
0'
#1445000
b11 *
1'
#1450000
0'
#1455000
b100 *
1'
#1460000
0'
#1465000
b101 *
1'
#1470000
0'
#1475000
b110 *
1'
#1480000
0'
#1485000
b111 *
1'
#1490000
0'
#1495000
b1000 *
1'
#1500000
0'
#1505000
b1001 *
1'
#1510000
0'
#1515000
b0 *
1)
1'
#1520000
0'
#1525000
b1 3
b1 *
0)
1'
#1530000
0'
#1535000
b10 *
1'
#1540000
0'
#1545000
b11 *
1'
#1550000
0'
#1555000
b100 *
1'
#1560000
0'
#1565000
b101 *
1'
#1570000
0'
#1575000
b110 *
1'
#1580000
0'
#1585000
b111 *
1'
#1590000
0'
#1595000
b1000 *
1'
#1600000
0'
#1605000
b1001 *
1'
#1610000
0'
#1615000
b0 *
1)
1'
#1620000
0'
#1625000
b10 3
b1 *
0)
1'
#1630000
0'
#1635000
b10 *
1'
#1640000
0'
#1645000
b11 *
1'
#1650000
0'
#1655000
b100 *
1'
#1660000
0'
#1665000
b101 *
1'
#1670000
0'
#1675000
b110 *
1'
#1680000
0'
#1685000
b111 *
1'
#1690000
0'
#1695000
b1000 *
1'
#1700000
0'
#1705000
b1001 *
1'
#1710000
0'
#1715000
b0 *
1)
1'
#1720000
0'
#1725000
b11 3
b1 *
0)
1'
#1730000
0'
#1735000
b10 *
1'
#1740000
0'
#1745000
b11 *
1'
#1750000
0'
#1755000
b100 *
1'
#1760000
0'
#1765000
b101 *
1'
#1770000
0'
#1775000
b110 *
1'
#1780000
0'
#1785000
b111 *
1'
#1790000
0'
#1795000
b1000 *
1'
#1800000
0'
#1805000
b1001 *
1'
#1810000
0'
#1815000
b0 *
1)
1'
#1820000
0'
#1825000
b100 3
b1 *
0)
1'
#1830000
0'
#1835000
b10 *
1'
#1840000
0'
#1845000
b11 *
1'
#1850000
0'
#1855000
b100 *
1'
#1860000
0'
#1865000
b101 *
1'
#1870000
0'
#1875000
b110 *
1'
#1880000
0'
#1885000
b111 *
1'
#1890000
0'
#1895000
b1000 *
1'
#1900000
0'
#1905000
b1001 *
1'
#1910000
0'
#1915000
b1 /
b0 *
1)
1'
#1920000
0'
#1925000
1!
12
1%
1-
0#
00
b1 +
b0 3
b1 *
0)
1'
#1930000
0'
#1935000
b10 *
1'
#1940000
0'
#1945000
b11 *
1'
#1950000
0'
#1955000
b100 *
1'
#1960000
0'
#1965000
b101 *
1'
#1970000
0'
#1975000
b110 *
1'
#1980000
0'
#1985000
b111 *
1'
#1990000
0'
#1995000
b1000 *
1'
#2000000
0'
#2005000
b1001 *
1'
#2010000
0'
#2015000
b0 *
1)
1'
