fsm-assignments/problem1_seqdet/seq_detect_mealy.v
module seq_detect_mealy(
    input  wire clk,
    input  wire rst,  // synchronous, active-high
    input  wire din,  // serial input bit per clock
    output wire y     // 1-cycle pulse when pattern ...1101 seen
);
    // State encoding
    parameter init = 2'b00; // no match
    parameter one   = 2'b01; // seen '1'
    parameter two  = 2'b10; // seen '11'
    parameter three = 2'b11; // seen '110'

    reg [1:0] state_present, state_next;

    // State register (sync reset)
    always @(posedge clk) begin
        if (rst) state_present <= init;
        else     state_present <= state_next;
    end

    // Next state logic
    always @(*) begin
        case (state_present)
            init:   if (din) state_next = one;   else state_next = init;
            one:   if (din) state_next = two;  else state_next = init;
            two:  if (din) state_next = two;  else state_next = three;
            three: if (din) state_next = one;   else state_next = init;
            default: state_next = init;
        endcase
    end

    // Mealy output logic (pulse when in three and din==1)
    assign y = (state_present == three && din);

endmodule

fsm-assignments/problem1_seqdet/tb_seq_detect_mealy.v
`timescale 1ns/1ps
`include "seq_detect_mealy.v"

// Testbench for seq_detect_mealy module
module tb_seq_detect_mealy;
    reg clk = 0;
    reg rst = 1;
    reg din = 0;
    wire y;

    seq_detect_mealy dut(
        .clk(clk), .rst(rst), .din(din), .y(y)
    );

    // 100 MHz clock (10 ns period)
    always #5 clk = ~clk;

    // Sync reset for 3 cycles
    initial begin
        repeat (3) @(posedge clk);
        rst <= 1'b0;
    end

    // Drive a bitstream with overlaps: 11011011101
    //    Also add a few extra clocks to observe stability
    reg [0:10] vec = 11'b11011011101; // MSB-first for readability
    integer i;
    initial begin
        // VCD
        $dumpfile("dump.vcd");
        $dumpvars(0, tb_seq_detect_mealy);

        // Wait reset deassertion boundary to align with posedge
        @(negedge rst);
        @(posedge clk);

        for (i = 0; i < 11; i = i + 1) begin
            din <= vec[i];
            @(posedge clk);
        end
        // Hold low afterwards
        din <= 1'b0;
        repeat (5) @(posedge clk);
        $finish;
    end

    // Log time, din, y, and state via hierarchical reference (for debug)
    //    Why: aids waveform-less debug and confirms overlap behavior.
    initial begin
        $display("  time  | clk rst din | y ");
        $display("--------------------------------");
        $monitor("%7t |  %0b   %0b   %0b | %0b",
                 $time, clk, rst, din, y);
    end
endmodule

fsm-assignments/problem1_seqdet/waves/dump.vcd
$date
	Tue Aug 19 19:58:42 2025
$end
$version
	Icarus Verilog
$end
$timescale
	1ps
$end
$scope module tb_seq_detect_mealy $end
$var wire 1 ! y $end
$var reg 1 " clk $end
$var reg 1 # din $end
$var reg 1 $ rst $end
$var reg 11 % vec [0:10] $end
$var integer 32 & i [31:0] $end
$scope module dut $end
$var wire 1 " clk $end
$var wire 1 # din $end
$var wire 1 $ rst $end
$var wire 1 ! y $end
$var reg 2 ' state_next [1:0] $end
$var reg 2 ( state_present [1:0] $end
$upscope $end
$upscope $end
$enddefinitions $end
#0
$dumpvars
bx (
b0 '
bx &
b11011011101 %
1$
0#
0"
0!
$end
#5000
b0 (
1"
#10000
0"
#15000
1"
#20000
0"
#25000
0$
1"
#30000
0"
#35000
b1 '
1#
b0 &
1"
#40000
0"
#45000
b10 '
b1 (
b1 &
1"
#50000
0"
#55000
b11 '
b10 (
0#
b10 &
1"
#60000
0"
#65000
b1 '
1!
1#
b11 (
b11 &
1"
#70000
0"
#75000
b10 '
0!
b1 (
b100 &
1"
#80000
0"
#85000
b11 '
0#
b10 (
b101 &
1"
#90000
0"
#95000
1!
b1 '
b11 (
1#
b110 &
1"
#100000
0"
#105000
b10 '
0!
b1 (
b111 &
1"
#110000
0"
#115000
b10 (
b1000 &
1"
#120000
0"
#125000
b11 '
0#
b1001 &
1"
#130000
0"
#135000
1!
b1 '
b11 (
1#
b1010 &
1"
#140000
0"
#145000
b0 '
0!
0#
b1 (
b1011 &
1"
#150000
0"
#155000
b0 (
1"
