fsm-assignments/problem3_vending/vending_mealy.v
module vending_mealy(
    input  wire clk,
    input  wire rst,      // synchronous, active-high
    input  wire [1:0] coin, // 01=5, 10=10, 00=idle (ignore 11)
    output wire dispense, // 1-cycle pulse when total >=20
    output wire chg5      // 1-cycle pulse when total==25
);
    // State encoding
    localparam [1:0]
        S0  = 2'b00,
        S5  = 2'b01,
        S10 = 2'b10,
        S15 = 2'b11;

    reg [1:0] state, next_state;
    reg dispense_c, chg5_c;

    // Next-state & Mealy outputs
    always @* begin
        next_state = state;
        dispense_c = 1'b0;
        chg5_c = 1'b0;
        case (state)
            S0: begin
                if (coin == 2'b01) next_state = S5;
                else if (coin == 2'b10) next_state = S10;
            end
            S5: begin
                if (coin == 2'b01) next_state = S10;
                else if (coin == 2'b10) next_state = S15;
            end
            S10: begin
                if (coin == 2'b01) next_state = S15;
                else if (coin == 2'b10) begin
                    dispense_c = 1'b1; // total=20
                    next_state = S0;
                end
            end
            S15: begin
                if (coin == 2'b01) begin
                    dispense_c = 1'b1; // total=20
                    next_state = S0;
                end else if (coin == 2'b10) begin
                    dispense_c = 1'b1; // total=25
                    chg5_c = 1'b1;
                    next_state = S0;
                end
            end
        endcase
    end

    // State register with synchronous reset
    always @(posedge clk) begin
        if (rst) state <= S0;
        else state <= next_state;
    end

    assign dispense = dispense_c;
    assign chg5 = chg5_c;
endmodule

fsm-assignments/problem3_vending/tb_vending_mealy.v
`timescale 1ns/1ps
`include "vending_mealy.v"

// Testbench for vending_mealy module
module tb_vending_mealy;
    reg clk = 0;
    reg rst = 1;
    reg [1:0] coin = 2'b00;
    wire dispense, chg5;

    vending_mealy dut(
        .clk(clk), .rst(rst), .coin(coin),
        .dispense(dispense), .chg5(chg5)
    );

    // 100 MHz clk
    always #5 clk = ~clk;

    // Reset
    initial begin
        repeat (3) @(posedge clk);
        rst <= 0;
    end

    // Drive sequences
    initial begin
        $dumpfile("dump.vcd");
        $dumpvars(0, tb_vending_mealy);

        @(negedge rst);
        @(posedge clk);

        // Test: 5+5+10=20
        coin <= 2'b01; @(posedge clk);
        coin <= 2'b00; @(posedge clk);
        coin <= 2'b01; @(posedge clk);
        coin <= 2'b00; @(posedge clk);
        coin <= 2'b10; @(posedge clk);
        coin <= 2'b00; @(posedge clk);

        // Test: 10+10=20
        coin <= 2'b10; @(posedge clk);
        coin <= 2'b00; @(posedge clk);
        coin <= 2'b10; @(posedge clk);
        coin <= 2'b00; @(posedge clk);

        // Test: 5+10+10=25 (dispense+chg5)
        coin <= 2'b01; @(posedge clk);
        coin <= 2'b00; @(posedge clk);
        coin <= 2'b10; @(posedge clk);
        coin <= 2'b00; @(posedge clk);
        coin <= 2'b10; @(posedge clk);
        coin <= 2'b00; @(posedge clk);

        repeat (5) @(posedge clk);
        $finish;
    end

    // Monitor
    initial begin
        $display(" time | coin dispense chg5");
        $display("-----------------------------");
        $monitor("%6t |  %02b      %0b      %0b",
                 $time, coin, dispense, chg5);
    end
endmodule

fsm-assignments/problem3_vending/waves/dump.vcd
$date
	Tue Aug 19 20:28:20 2025
$end
$version
	Icarus Verilog
$end
$timescale
	1ps
$end
$scope module tb_vending_mealy $end
$var wire 1 ! dispense $end
$var wire 1 " chg5 $end
$var reg 1 # clk $end
$var reg 2 $ coin [1:0] $end
$var reg 1 % rst $end
$scope module dut $end
$var wire 1 " chg5 $end
$var wire 1 # clk $end
$var wire 2 & coin [1:0] $end
$var wire 1 ! dispense $end
$var wire 1 % rst $end
$var reg 1 ' chg5_c $end
$var reg 1 ( dispense_c $end
$var reg 2 ) next_state [1:0] $end
$var reg 2 * state [1:0] $end
$upscope $end
$upscope $end
$enddefinitions $end
#0
$dumpvars
bx *
bx )
0(
0'
b0 &
1%
b0 $
0#
0"
0!
$end
#5000
b0 )
b0 *
1#
#10000
0#
#15000
1#
#20000
0#
#25000
0%
1#
#30000
0#
#35000
b1 )
b1 $
b1 &
1#
#40000
0#
#45000
b0 $
b0 &
b1 *
1#
#50000
0#
#55000
b10 )
b1 $
b1 &
1#
#60000
0#
#65000
b0 $
b0 &
b10 *
1#
#70000
0#
#75000
b0 )
1!
1(
b10 $
b10 &
1#
#80000
0#
#85000
0!
0(
b0 $
b0 &
b0 *
1#
#90000
0#
#95000
b10 )
b10 $
b10 &
1#
#100000
0#
#105000
b0 $
b0 &
b10 *
1#
#110000
0#
#115000
b0 )
1!
1(
b10 $
b10 &
1#
#120000
0#
#125000
0!
0(
b0 $
b0 &
b0 *
1#
#130000
0#
#135000
b1 )
b1 $
b1 &
1#
#140000
0#
#145000
b0 $
b0 &
b1 *
1#
#150000
0#
#155000
b11 )
b10 $
b10 &
1#
#160000
0#
#165000
b0 $
b0 &
b11 *
1#
#170000
0#
#175000
b0 )
1"
1'
1!
1(
b10 $
b10 &
1#
#180000
0#
#185000
0"
0'
0!
0(
b0 $
b0 &
b0 *
1#
