fsm-assignments/problem4_link/slave_fsm.v
module slave_fsm(
    input  wire clk,
    input  wire rst,
    input  wire req,
    input  wire [7:0] data_in,
    output reg  ack,
    output reg  [7:0] last_byte
);
    localparam [1:0] IDLE=2'd0, ACK1=2'd1, ACK2=2'd2;

    reg [1:0] state, next_state;
    reg [7:0] next_last;
    reg next_ack;

    always @* begin
        next_state = state;
        next_ack   = ack;
        next_last  = last_byte;

        case (state)
            IDLE: begin
                if (req) begin
                    next_last  = data_in;
                    next_ack   = 1'b1;
                    next_state = ACK1;
                end
            end
            ACK1: begin
                next_state = ACK2;
            end
            ACK2: begin
                next_ack   = 1'b0;
                next_state = IDLE;
            end
        endcase
    end

    always @(posedge clk) begin
        if (rst) begin
            state     <= IDLE;
            ack       <= 1'b0;
            last_byte <= 8'h00;
        end else begin
            state     <= next_state;
            ack       <= next_ack;
            last_byte <= next_last;
        end
    end
endmodule

fsm-assignments/problem4_link/master_fsm.v
module master_fsm(
    input  wire clk,
    input  wire rst,   // sync active-high
    input  wire ack,
    output reg  req,
    output reg  [7:0] data,
    output reg  done
);
    localparam [2:0]
        IDLE        = 3'd0,
        SEND        = 3'd1,
        WAIT_ACK    = 3'd2,
        WAIT_ACK_LO = 3'd3,
        DONE        = 3'd4;

    reg [2:0] state, next_state;
    reg [1:0] byte_idx, next_idx;
    reg [7:0] next_data;
    reg next_req, next_done;

    // fixed data sequence A0..A3
    function [7:0] byte_val(input [1:0] idx);
        case (idx)
            2'd0: byte_val = 8'hA0;
            2'd1: byte_val = 8'hA1;
            2'd2: byte_val = 8'hA2;
            2'd3: byte_val = 8'hA3;
        endcase
    endfunction

    always @* begin
        next_state = state;
        next_idx   = byte_idx;
        next_data  = data;
        next_req   = req;
        next_done  = 1'b0;

        case (state)
            IDLE: begin
                next_idx   = 0;
                next_data  = byte_val(0);
                next_req   = 1'b1;
                next_state = SEND;
            end
            SEND: begin
                next_state = WAIT_ACK;
            end
            WAIT_ACK: begin
                if (ack) begin
                    next_req   = 1'b0; // drop req
                    next_state = WAIT_ACK_LO;
                end
            end
            WAIT_ACK_LO: begin
                if (!ack) begin
                    if (byte_idx == 2'd3) begin
                        next_done  = 1'b1;
                        next_state = DONE;
                    end else begin
                        next_idx   = byte_idx + 1;
                        next_data  = byte_val(byte_idx + 1);
                        next_req   = 1'b1;
                        next_state = SEND;
                    end
                end
            end
            DONE: begin
                next_state = DONE;
            end
        endcase
    end

    always @(posedge clk) begin
        if (rst) begin
            state    <= IDLE;
            byte_idx <= 0;
            data     <= 8'h00;
            req      <= 1'b0;
            done     <= 1'b0;
        end else begin
            state    <= next_state;
            byte_idx <= next_idx;
            data     <= next_data;
            req      <= next_req;
            done     <= next_done;
        end
    end
endmodule

fsm-assignments/problem4_link/link_top.v
`timescale 1ns/1ps
`include "master_fsm.v"
`include "slave_fsm.v"
module link_top(
    input  wire clk,
    input  wire rst,
    output wire done
);
    wire req, ack;
    wire [7:0] data;
    wire [7:0] last;

    master_fsm u_master(
        .clk(clk), .rst(rst), .ack(ack),
        .req(req), .data(data), .done(done)
    );

    slave_fsm u_slave(
        .clk(clk), .rst(rst), .req(req), .data_in(data),
        .ack(ack), .last_byte(last)
    );
endmodule

fsm-assignments/problem4_link/tb_link_top.v
`timescale 1ns/1ps
`include "link_top.v"

module tb_link_top;
    reg clk = 0;
    reg rst = 1;
    wire done;

    link_top dut(.clk(clk), .rst(rst), .done(done));

    // clock
    always #5 clk = ~clk;

    // reset
    initial begin
        repeat (3) @(posedge clk);
        rst <= 0;
    end

    // sim control
    initial begin
        $dumpfile("dump.vcd");
        $dumpvars(0, tb_link_top);
        wait(done);
        repeat (5) @(posedge clk);
        $finish;
    end

    // monitor handshake
    initial begin
        $display(" time | req ack data done");
        $display("---------------------------");
        $monitor("%6t |  %0b   %0b  %02h   %0b",
                 $time,
                 dut.u_master.req,
                 dut.u_slave.ack,
                 dut.u_master.data,
                 done);
    end
endmodule

fsm-assignments/problem4_link/waves/dump.vcd
$date
	Tue Aug 19 20:34:50 2025
$end
$version
	Icarus Verilog
$end
$timescale
	1ps
$end
$scope module tb_link_top $end
$var wire 1 ! done $end
$var reg 1 " clk $end
$var reg 1 # rst $end
$scope module dut $end
$var wire 1 " clk $end
$var wire 1 # rst $end
$var wire 1 $ req $end
$var wire 8 % last [7:0] $end
$var wire 1 ! done $end
$var wire 8 & data [7:0] $end
$var wire 1 ' ack $end
$scope module u_master $end
$var wire 1 " clk $end
$var wire 1 # rst $end
$var wire 1 ' ack $end
$var reg 2 ( byte_idx [1:0] $end
$var reg 8 ) data [7:0] $end
$var reg 1 ! done $end
$var reg 8 * next_data [7:0] $end
$var reg 1 + next_done $end
$var reg 2 , next_idx [1:0] $end
$var reg 1 - next_req $end
$var reg 3 . next_state [2:0] $end
$var reg 1 $ req $end
$var reg 3 / state [2:0] $end
$scope function byte_val $end
$var reg 2 0 idx [1:0] $end
$upscope $end
$upscope $end
$scope module u_slave $end
$var wire 1 " clk $end
$var wire 8 1 data_in [7:0] $end
$var wire 1 $ req $end
$var wire 1 # rst $end
$var reg 1 ' ack $end
$var reg 8 2 last_byte [7:0] $end
$var reg 1 3 next_ack $end
$var reg 8 4 next_last [7:0] $end
$var reg 2 5 next_state [1:0] $end
$var reg 2 6 state [1:0] $end
$upscope $end
$upscope $end
$upscope $end
$enddefinitions $end
#0
$dumpvars
bx 6
bx 5
bx 4
x3
bx 2
bx 1
bx 0
bx /
bx .
x-
bx ,
x+
bx *
bx )
bx (
x'
bx &
bx %
x$
1#
0"
x!
$end
#5000
b0 0
0+
1-
b10100000 *
b0 ,
b1 .
b0 4
03
b0 5
0!
0$
b0 &
b0 )
b0 1
b0 (
b0 /
b0 %
b0 2
0'
b0 6
1"
#10000
0"
#15000
1"
#20000
0"
#25000
0#
1"
#30000
0"
#35000
b1 5
13
b10100000 4
b10 .
1$
b10100000 &
b10100000 )
b10100000 1
b1 /
1"
#40000
0"
#45000
b11 .
0-
b10 5
b10 /
b10100000 %
b10100000 2
1'
b1 6
1"
#50000
0"
#55000
b0 5
03
b10 6
0$
b11 /
1"
#60000
0"
#65000
b1 .
1-
b10100001 *
b1 0
b1 ,
0'
b0 6
1"
#70000
0"
#75000
b1 5
13
b10100001 4
b10 .
1$
b10100001 &
b10100001 )
b10100001 1
b1 (
b1 /
1"
#80000
0"
#85000
b11 .
0-
b10 5
b10 /
b10100001 %
b10100001 2
1'
b1 6
1"
#90000
0"
#95000
b0 5
03
b10 6
0$
b11 /
1"
#100000
0"
#105000
b1 .
1-
b10100010 *
b10 0
b10 ,
0'
b0 6
1"
#110000
0"
#115000
b1 5
13
b10100010 4
b10 .
1$
b10100010 &
b10100010 )
b10100010 1
b10 (
b1 /
1"
#120000
0"
#125000
b11 .
0-
b10 5
b10 /
b10100010 %
b10100010 2
1'
b1 6
1"
#130000
0"
#135000
b0 5
03
b10 6
0$
b11 /
1"
#140000
0"
#145000
b1 .
1-
b10100011 *
b11 0
b11 ,
0'
b0 6
1"
#150000
0"
#155000
b1 5
13
b10100011 4
b10 .
1$
b10100011 &
b10100011 )
b10100011 1
b11 (
b1 /
1"
#160000
0"
#165000
b11 .
0-
b10 5
b10 /
b10100011 %
b10100011 2
1'
b1 6
1"
#170000
0"
#175000
b0 5
03
b10 6
0$
b11 /
1"
#180000
0"
#185000
b100 .
1+
0'
b0 6
1"
#190000
0"
#195000
0+
1!
b100 /
1"
#200000
0"
#205000
0!
1"
